vall/__init__.py
vall/macros.py
vall/data/__init__.py
vall/data/collation.py
vall/data/datamodule.py
vall/data/dataset.py
vall/data/fbank.py
vall/data/input_strategies.py
vall/data/tokenizer.py
vall/models/__init__.py
vall/models/macros.py
vall/models/transformer.py
vall/models/vallex.py
vall/models/visualizer.py
vall/modules/__init__.py
vall/modules/activation.py
vall/modules/embedding.py
vall/modules/optim.py
vall/modules/scaling.py
vall/modules/scheduler.py
vall/modules/transformer.py
vall/utils/__init__.py
vall/utils/download.py
vall/utils/generation.py
vall/utils/prompt_making.py
vall/utils/sentence_cutter.py
vall/utils/symbol_table.py
vall/utils/g2p/__init__.py
vall/utils/g2p/bpe_1024.json
vall/utils/g2p/bpe_69.json
vall/utils/g2p/cleaners.py
vall/utils/g2p/english.py
vall/utils/g2p/japanese.py
vall/utils/g2p/mandarin.py
vall/utils/g2p/symbols.py
langs_vall-0.0.18.dist-info/METADATA
langs_vall-0.0.18.dist-info/WHEEL
langs_vall-0.0.18.dist-info/top_level.txt
langs_vall-0.0.18.dist-info/RECORD
